tilingpuzzles/__init__.py
tilingpuzzles/logger.py
tilingpuzzles/benchmark/__init__.py
tilingpuzzles/benchmark/git_state.py
tilingpuzzles/benchmark/run_benchmark.py
tilingpuzzles/benchmark/data/timingResulsts.csv
tilingpuzzles/examples/README.md
tilingpuzzles/examples/__init__.py
tilingpuzzles/examples/rectangularPentomino.py
tilingpuzzles/examples/scaledStones.py
tilingpuzzles/examples/tests/__init__.py
tilingpuzzles/examples/tests/test_rectangularPentomino.py
tilingpuzzles/examples/tests/test_scaledStones.py
tilingpuzzles/games/__init__.py
tilingpuzzles/games/game.py
tilingpuzzles/games/generic.py
tilingpuzzles/games/komino.py
tilingpuzzles/games/realisations.py
tilingpuzzles/games/stone.py
tilingpuzzles/games/stone_core.py
tilingpuzzles/games/tile.py
tilingpuzzles/games/tests/__init__.py
tilingpuzzles/games/tests/test_game.py
tilingpuzzles/games/tests/test_komino.py
tilingpuzzles/games/tests/test_realisations.py
tilingpuzzles/games/tests/test_stone.py
tilingpuzzles/games/tests/test_tile.py
tilingpuzzles/solvers/__init__.py
tilingpuzzles/solvers/hights.py
tilingpuzzles/solvers/kominoSolver.py
tilingpuzzles/solvers/tests/test_komino_solver.py
tilingpuzzles/visualize/__init__.py
tilingpuzzles/visualize/visualize.py
tilingpuzzles-0.2.4.dist-info/METADATA
tilingpuzzles-0.2.4.dist-info/WHEEL
tilingpuzzles-0.2.4.dist-info/entry_points.txt
tilingpuzzles-0.2.4.dist-info/RECORD
