Metadata-Version: 2.4
Name: tilingPuzzles
Version: 0.2.4
Summary: finding and counting solutions of tilingpuzzles like Pentomino
Author-email: jonathan graf <jonathangraf@outlook.de>
Requires-Python: >=3.10
Requires-Dist: jupyter>=1.1.1
Requires-Dist: matplotlib>=3.10.3
Requires-Dist: numpy>=2.2.6
Requires-Dist: pandas>=2.2.3
Requires-Dist: py-cpuinfo>=9.0.0
Requires-Dist: pytest>=8.3.5
Requires-Dist: timeout-decorator>=0.5.0
Requires-Dist: tqdm>=4.67.1
